snakepack/__init__.py
snakepack/__main__.py
snakepack/analyzers/__init__.py
snakepack/analyzers/_base.py
snakepack/analyzers/python/__init__.py
snakepack/analyzers/python/_base.py
snakepack/analyzers/python/imports.py
snakepack/analyzers/python/literals.py
snakepack/analyzers/python/scope.py
snakepack/app.py
snakepack/assets/__init__.py
snakepack/assets/_base.py
snakepack/assets/generic.py
snakepack/assets/python.py
snakepack/bundlers/__init__.py
snakepack/bundlers/_base.py
snakepack/bundlers/generic.py
snakepack/compiler.py
snakepack/config/__init__.py
snakepack/config/_base.py
snakepack/config/formats.py
snakepack/config/model.py
snakepack/config/options.py
snakepack/config/types.py
snakepack/loaders/__init__.py
snakepack/loaders/_base.py
snakepack/loaders/generic.py
snakepack/loaders/python.py
snakepack/packagers/__init__.py
snakepack/packagers/_base.py
snakepack/packagers/generic.py
snakepack/transformers/__init__.py
snakepack/transformers/_base.py
snakepack/transformers/python/__init__.py
snakepack/transformers/python/_base.py
snakepack/transformers/python/_renaming.py
snakepack/transformers/python/hoist_literals.py
snakepack/transformers/python/remove_annotations.py
snakepack/transformers/python/remove_assertions.py
snakepack/transformers/python/remove_comments.py
snakepack/transformers/python/remove_literal_statements.py
snakepack/transformers/python/remove_object_base.py
snakepack/transformers/python/remove_parameter_separators.py
snakepack/transformers/python/remove_pass.py
snakepack/transformers/python/remove_semicolons.py
snakepack/transformers/python/remove_unreferenced_code.py
snakepack/transformers/python/remove_whitespace.py
snakepack/transformers/python/rename_identifiers.py
snakepack-0.1.0.dist-info/entry_points.txt
snakepack-0.1.0.dist-info/WHEEL
snakepack-0.1.0.dist-info/METADATA
snakepack-0.1.0.dist-info/RECORD
