Metadata-Version: 2.1
Name: snakepack
Version: 0.1.0
Summary: 
Author: Jochen Van de Velde
Author-email: mail@jochenvandevelde.be
Requires-Python: >=3.8,<=3.10
Classifier: Programming Language :: Python :: 3
Classifier: Programming Language :: Python :: 3.10
Classifier: Programming Language :: Python :: 3.8
Classifier: Programming Language :: Python :: 3.9
Requires-Dist: PyYAML (>=6.0,<7.0)
Requires-Dist: boltons (>=21.0.0,<22.0.0)
Requires-Dist: click (>=8.0.3,<9.0.0)
Requires-Dist: cloudpickle (>=2.0.0,<3.0.0)
Requires-Dist: libcst (>=0.3.21,<0.4.0)
Requires-Dist: loky (>=3.0.0,<4.0.0)
Requires-Dist: modulegraph (>=0.19.2,<0.20.0)
Requires-Dist: pydantic (>=1.8.2,<2.0.0)
Requires-Dist: stdlib-list (>=0.8.0,<0.9.0)
